scapi.py
scapi_py-2.0.4.dist-info/METADATA
scapi_py-2.0.4.dist-info/WHEEL
scapi_py-2.0.4.dist-info/entry_points.txt
scapi_py-2.0.4.dist-info/licenses/LICENSE
scapi_py-2.0.4.dist-info/RECORD
