Metadata-Version: 2.4
Name: scapi-py
Version: 2.0.4
Summary: Dead simple, self-contained, single-file API load testing tool built on FastAPI.
Project-URL: Source code, https://github.com/sesav/scapi-py
Author-email: Sergey Silaev <hello@8am.dev>
License-Expression: MIT
License-File: LICENSE
Keywords: api,fastapi,load,python,python310,python311,python312,python313,single-file,testing,tool
Classifier: Development Status :: 5 - Production/Stable
Classifier: Environment :: Web Environment
Classifier: Framework :: AsyncIO
Classifier: Framework :: FastAPI
Classifier: Framework :: Pydantic
Classifier: Intended Audience :: Developers
Classifier: Intended Audience :: Information Technology
Classifier: Intended Audience :: System Administrators
Classifier: License :: OSI Approved :: MIT License
Classifier: Operating System :: OS Independent
Classifier: Programming Language :: Python
Classifier: Programming Language :: Python :: 3
Classifier: Programming Language :: Python :: 3.10
Classifier: Programming Language :: Python :: 3.11
Classifier: Programming Language :: Python :: 3.12
Classifier: Programming Language :: Python :: 3.13
Classifier: Topic :: Education :: Testing
Classifier: Topic :: Internet
Classifier: Topic :: Internet :: WWW/HTTP
Classifier: Topic :: Internet :: WWW/HTTP :: HTTP Servers
Classifier: Topic :: Software Development
Classifier: Topic :: Software Development :: Libraries
Classifier: Topic :: Software Development :: Libraries :: Python Modules
Classifier: Topic :: Software Development :: Testing
Classifier: Topic :: Software Development :: Testing :: Traffic Generation
Requires-Python: >=3.10
Requires-Dist: fastapi==0.116.1
Requires-Dist: httpx==0.28.1
Requires-Dist: pydantic>=2.11.7
Requires-Dist: structlog==25.1.0
Requires-Dist: uvicorn==0.35.0
Requires-Dist: uvloop==0.21.0
